eq_sql_connector/__init__.py
eq_sql_connector/connector.py
eq_sql_connector-0.1.0.dist-info/LICENSE
eq_sql_connector-0.1.0.dist-info/METADATA
eq_sql_connector-0.1.0.dist-info/WHEEL
eq_sql_connector-0.1.0.dist-info/RECORD
